aquacrop/__init__.py
aquacrop/aquacrop.py
aquacrop/base.py
aquacrop/constants.py
aquacrop/output.py
aquacrop/entities/__init__.py
aquacrop/entities/calendar.py
aquacrop/entities/climate.py
aquacrop/entities/crop.py
aquacrop/entities/ground_water.py
aquacrop/entities/initial_conditions.py
aquacrop/entities/irrigation.py
aquacrop/entities/management.py
aquacrop/entities/observation.py
aquacrop/entities/off_season.py
aquacrop/entities/parameter.py
aquacrop/entities/soil.py
aquacrop/file_generators/__init__.py
aquacrop/file_generators/DATA/__init__.py
aquacrop/file_generators/DATA/cal_generator.py
aquacrop/file_generators/DATA/cli_generator.py
aquacrop/file_generators/DATA/co2_generator.py
aquacrop/file_generators/DATA/crop_generator.py
aquacrop/file_generators/DATA/eto_generator.py
aquacrop/file_generators/DATA/gwt_generator.py
aquacrop/file_generators/DATA/irr_generator.py
aquacrop/file_generators/DATA/man_generator.py
aquacrop/file_generators/DATA/off_generator.py
aquacrop/file_generators/DATA/plu_generator.py
aquacrop/file_generators/DATA/sol_generator.py
aquacrop/file_generators/DATA/sw0_generator.py
aquacrop/file_generators/DATA/tnx_generator.py
aquacrop/file_generators/LIST/__init__.py
aquacrop/file_generators/LIST/list_projects_generator.py
aquacrop/file_generators/LIST/prm_generator.py
aquacrop/file_generators/OBS/__init__.py
aquacrop/file_generators/OBS/obs_generator.py
aquacrop/file_generators/PARAM/__init__.py
aquacrop/file_generators/PARAM/ppn_generator.py
aquacrop/file_generators/SIMUL/__init__.py
aquacrop/file_generators/SIMUL/aggregation_result_generator.py
aquacrop/file_generators/SIMUL/daily_results_generator.py
aquacrop/file_generators/SIMUL/particular_result_generator.py
aquacrop/templates/__init__.py
aquacrop/templates/default_calendars.py
aquacrop/templates/default_climate.py
aquacrop/templates/default_crops.py
aquacrop/templates/default_groundwater.py
aquacrop/templates/default_initial_conditions.py
aquacrop/templates/default_irrigation.py
pyaquacrop-0.1.4.dist-info/licenses/LICENSE
pyaquacrop-0.1.4.dist-info/METADATA
pyaquacrop-0.1.4.dist-info/WHEEL
pyaquacrop-0.1.4.dist-info/top_level.txt
pyaquacrop-0.1.4.dist-info/RECORD
