Metadata-Version: 2.4
Name: pyaquacrop
Version: 0.1.4
Summary: Python wrapper for the AquaCrop crop growth model
Author-email: Francisco Puig <g32pupef@uco.es>
License: MIT
Project-URL: Homepage, https://github.com/pacs27/pyaquacrop
Project-URL: Bug Tracker, https://github.com/pacs27/pyaquacrop/issues
Classifier: Development Status :: 3 - Alpha
Classifier: Intended Audience :: Science/Research
Classifier: Topic :: Scientific/Engineering :: GIS
Classifier: Programming Language :: Python :: 3.11
Requires-Python: >=3.8
License-File: LICENSE
Requires-Dist: pytest==8.3.3
Requires-Dist: pandas==2.2.2
Dynamic: license-file
